fractal_slurm_tools/__init__.py
fractal_slurm_tools/errors.py
fractal_slurm_tools/parse_job_folders.py
fractal_slurm_tools/parse_sacct_info.py
fractal_slurm_tools/run_sacct_command.py
fractal_slurm_tools/sacct_fields.py
fractal_slurm_tools/sacct_parser_functions.py
fractal_slurm_tools/sacct_parsers.py
fractal_slurm_tools/aggregate/_aggregate.py
fractal_slurm_tools/aggregate/cli.py
fractal_slurm_tools/parse_bulk/_parse_bulk.py
fractal_slurm_tools/parse_bulk/cli.py
fractal_slurm_tools/parse_single_job/_parse_single_job.py
fractal_slurm_tools/parse_single_job/cli.py
fractal_slurm_tools-0.1.1.dist-info/licenses/LICENSE
fractal_slurm_tools-0.1.1.dist-info/METADATA
fractal_slurm_tools-0.1.1.dist-info/WHEEL
fractal_slurm_tools-0.1.1.dist-info/entry_points.txt
fractal_slurm_tools-0.1.1.dist-info/top_level.txt
fractal_slurm_tools-0.1.1.dist-info/RECORD
