Metadata-Version: 2.4
Name: fractal-slurm-tools
Version: 0.1.1
Summary: Shared tools for parsing&processing SLURM data
Author-email: Tommaso Comparin <tommaso.comparin@exact-lab.it>
License: BSD-3-Clause
Project-URL: homepage, https://github.com/fractal-analytics-platform/fractal-slurm-tools
Project-URL: repository, https://github.com/fractal-analytics-platform/fractal-slurm-tools
Project-URL: changelog, https://github.com/fractal-analytics-platform/fractal-slurm-tools/blob/main/CHANGELOG.md
Requires-Python: <3.14,>=3.10
License-File: LICENSE
Requires-Dist: humanfriendly==10.0.0
Requires-Dist: requests
Requires-Dist: pandas<3.0,>=2.0
Requires-Dist: numpy
Provides-Extra: dev
Requires-Dist: bumpver==2024.1130; extra == "dev"
Requires-Dist: devtools==0.12.2; extra == "dev"
Requires-Dist: pytest<9.0.0,>=8.3.0; extra == "dev"
Requires-Dist: coverage<7.7.0,>=7.6.0; extra == "dev"
Requires-Dist: types-humanfriendly; extra == "dev"
Requires-Dist: types-requests; extra == "dev"
Requires-Dist: pandas-stubs; extra == "dev"
Requires-Dist: mypy; extra == "dev"
Dynamic: license-file
